redis_cache_lock/__init__.py
redis_cache_lock/enums.py
redis_cache_lock/exc.py
redis_cache_lock/main.py
redis_cache_lock/redis_utils.py
redis_cache_lock/scripts.py
redis_cache_lock/scripts_support.py
redis_cache_lock/types.py
redis_cache_lock/utils.py
redis_cache_lock-3.5.dist-info/LICENSE
redis_cache_lock-3.5.dist-info/WHEEL
redis_cache_lock-3.5.dist-info/METADATA
redis_cache_lock-3.5.dist-info/RECORD
